{
  "updatedAt": "2026-06-04",
  "count": 33,
  "artifacts": [
    {
      "name": "Nghịch Thiên châu (Thần Bí Hạt Châu)",
      "category": "baovat",
      "categoryLabel": "Pháp bảo / Bảo vật",
      "status": "known",
      "blurb": "Bảo vật then chốt của Vương Lâm — hạt châu xám khắc đám mây, chứa Mộng Cảnh không gian gia tốc thời gian (~10:1) và thực thể cố vấn Tư Đồ Nam. Là gốc rễ mọi kỳ tích của Vương Lâm và là thứ Cự Ma tộc truy lùng.",
      "detail": [
        {
          "label": "Nguồn gốc / hình dạng",
          "text": "Hạt châu màu xám khắc đám mây trắng, Vương Lâm nhặt được trong xác phi điểu ở phong nhãn (Ch.8). Ban đầu chỉ biết dùng để tiết sương chữa thương và ngâm nước tạo linh khí (số mây trên châu tự tăng 5 → 9 → 10). Thực chất là một pháp bảo cấp cực cao (Cự Ma tộc treo thưởng tầm Anh Biến), tên thật là Nghịch Thiên châu."
        },
        {
          "label": "Mộng Cảnh không gian",
          "text": "Khi đủ 10 mây, châu mở ra Mộng Cảnh không gian — một thế giới riêng có tỷ lệ thời gian nhanh gấp ~10 lần bên ngoài (2 tháng thực ≈ 1 năm tu trong mộng). Mỗi ngày vào được khoảng 3 lần, mỗi lần ~50 giờ. Đây là 'bí mật lớn nhất' giúp Vương Lâm bù đắp tư chất kém: tu luyện, luyện đan, né truy sát (100 ngày Tru Sát Lệnh), trốn Bát Cực Ma Quân đều nhờ không gian này."
        },
        {
          "label": "Ngũ Hành thuộc tính",
          "text": "Châu hấp thu thuộc tính ngũ hành để mạnh lên. Tới Ch.140 đã viên mãn Thủy + Mộc + Hỏa; còn thiếu Kim và Thổ để hoàn thành Ngũ Hành — một mạch truyện dài đang treo."
        },
        {
          "label": "Tư Đồ Nam & hồn cha mẹ",
          "text": "Sau Ch.100, Nguyên Anh Tư Đồ Nam (ân nhân cứu Vương Lâm) bọc hồn phách cha mẹ hắn vào Nguyên Anh rồi ngủ sâu bên trong Mộng Cảnh. Vương Lâm thề đạt Anh Biến kỳ sẽ tìm thân thể đưa Tư Đồ Nam ra và lo cho cha mẹ."
        },
        {
          "label": "Tỏa 'quang ban' nhập cơ thể",
          "text": "Châu từng tỏa 'quang ban' (vệt sáng) cổ quái nhập vào cơ thể Vương Lâm (Ch.8, 22-24, 38) — tác dụng đầy đủ chưa rõ, là một foreshadowing."
        },
        {
          "label": "Vai trò / hiện trạng",
          "text": "Pháp bảo định mệnh, gắn với Vương Lâm từ đầu truyện và là động lực bị Cự Ma tộc (ngũ cấp Vực Ngoại) truy lùng. Vẫn theo Vương Lâm xuyên suốt; mục tiêu hoàn thiện Ngũ Hành và giải cứu Tư Đồ Nam là hai mạch treo lớn."
        }
      ]
    },
    {
      "name": "Thôn phệ Kim Đan / Thông Phệ đại pháp",
      "category": "congphap",
      "categoryLabel": "Công pháp",
      "status": "known",
      "blurb": "Công pháp Tà Ma Tông cho phép **hấp thu một thành linh lực của Kim Đan** (qua đánh bại Kết Đan kỳ) → đẩy tu vi vọt lên. Vương Lâm dùng để lên Giả Đan cảnh giới (Ch.122). (Đại Tự Tại Tu La thuật hấp thu được hai thành nhưng Vương Lâm chưa tu chính.)",
      "detail": [
        {
          "label": "Mô tả",
          "text": "Công pháp Tà Ma Tông cho phép **hấp thu một thành linh lực của Kim Đan** (qua đánh bại Kết Đan kỳ) → đẩy tu vi vọt lên. Vương Lâm dùng để lên Giả Đan cảnh giới (Ch.122). (Đại Tự Tại Tu La thuật hấp thu được hai thành nhưng Vương Lâm chưa tu chính.)"
        }
      ]
    },
    {
      "name": "Luyện khí thuật Chiến Thần Điện (Điều - Dung - Hợp)",
      "category": "congphap",
      "categoryLabel": "Công pháp",
      "status": "known",
      "blurb": "Ba bước Điều - Dung - Hợp. Vương Lâm thử thất bại ở Ch.118 nhưng đến Ch.127 đã **thành thạo** — phá vô số thú cốt cốt hải để luyện Phiên Ưng lô và Thủy tinh phi kiếm.",
      "detail": [
        {
          "label": "Mô tả",
          "text": "Ba bước Điều - Dung - Hợp. Vương Lâm thử thất bại ở Ch.118 nhưng đến Ch.127 đã **thành thạo** — phá vô số thú cốt cốt hải để luyện Phiên Ưng lô và Thủy tinh phi kiếm."
        }
      ]
    },
    {
      "name": "Vạn Ma Bách Nhật Tru Sát Lệnh",
      "category": "baovat",
      "categoryLabel": "Pháp bảo / Bảo vật",
      "status": "known",
      "blurb": "Lệnh bài thượng cổ. Cơ chế: kẻ giết người mở lệnh sẽ bị **truy sát 100 ngày** (trên đầu hiện chữ đỏ máu \"Tru/Diệt\" làm dấu); ai giết được kẻ bị truy trong 100 ngày sẽ **đoạt toàn bộ tu vi** kẻ mở lệnh qua \"tu đan\". Nếu sống qua 100 ngày, chữ chuyển xám trắng và người bị truy **đoạt được tu vi kẻ mở ",
      "detail": [
        {
          "label": "Mô tả",
          "text": "Lệnh bài thượng cổ. Cơ chế: kẻ giết người mở lệnh sẽ bị **truy sát 100 ngày** (trên đầu hiện chữ đỏ máu \"Tru/Diệt\" làm dấu); ai giết được kẻ bị truy trong 100 ngày sẽ **đoạt toàn bộ tu vi** kẻ mở lệnh qua \"tu đan\". Nếu sống qua 100 ngày, chữ chuyển xám trắng và người bị truy **đoạt được tu vi kẻ mở lệnh**. Tiễn Khôn dùng để dọa Vương Lâm; Vương Lâm vẫn giết hắn rồi trốn 100 ngày trong Mộng Cảnh."
        }
      ]
    },
    {
      "name": "Tu đan",
      "category": "baovat",
      "categoryLabel": "Pháp bảo / Bảo vật",
      "status": "known",
      "blurb": "Kết tinh tổng tu vi của kẻ mở Tru Sát Lệnh, hình thành sau khi người bị truy sống qua 100 ngày (Ch.138). Vương Lâm cất **tu đan của Tiễn Khôn** để dùng khi Kết Anh.",
      "detail": [
        {
          "label": "Mô tả",
          "text": "Kết tinh tổng tu vi của kẻ mở Tru Sát Lệnh, hình thành sau khi người bị truy sống qua 100 ngày (Ch.138). Vương Lâm cất **tu đan của Tiễn Khôn** để dùng khi Kết Anh."
        }
      ]
    },
    {
      "name": "Thiên Ly đan",
      "category": "dandung",
      "categoryLabel": "Đan dược",
      "status": "known",
      "blurb": "Đan tăng tỷ lệ kết đan thành công. **Động cơ cốt lõi của Vương Lâm trong tuyến Tuyên Vũ quốc** (Ch.121). Lý Mộ Uyển luyện được (lần hai dùng Ma Huyết đằng thành công) — viên đan trực tiếp giúp Vương Lâm kết đan giữa vòng vây (Ch.127).",
      "detail": [
        {
          "label": "Mô tả",
          "text": "Đan tăng tỷ lệ kết đan thành công. **Động cơ cốt lõi của Vương Lâm trong tuyến Tuyên Vũ quốc** (Ch.121). Lý Mộ Uyển luyện được (lần hai dùng Ma Huyết đằng thành công) — viên đan trực tiếp giúp Vương Lâm kết đan giữa vòng vây (Ch.127)."
        }
      ]
    },
    {
      "name": "Lập Anh đan",
      "category": "dandung",
      "categoryLabel": "Đan dược",
      "status": "known",
      "blurb": "Đan cực hiếm tăng tỷ lệ **Kết Anh** (Kết Đan → Nguyên Anh). Bát Cực Ma Quân dùng làm mồi nhử trong giao ước (Ch.140).",
      "detail": [
        {
          "label": "Mô tả",
          "text": "Đan cực hiếm tăng tỷ lệ **Kết Anh** (Kết Đan → Nguyên Anh). Bát Cực Ma Quân dùng làm mồi nhử trong giao ước (Ch.140)."
        }
      ]
    },
    {
      "name": "Anh Biến đan",
      "category": "dandung",
      "categoryLabel": "Đan dược",
      "status": "known",
      "blurb": "Đan truyền thuyết liên quan tới Anh Biến kỳ, nằm trong số kho báu ở \"địa phương kia\" mà Bát Cực Ma Quân nhắc (Ch.140).",
      "detail": [
        {
          "label": "Mô tả",
          "text": "Đan truyền thuyết liên quan tới Anh Biến kỳ, nằm trong số kho báu ở \"địa phương kia\" mà Bát Cực Ma Quân nhắc (Ch.140)."
        }
      ]
    },
    {
      "name": "Thủy tinh phi kiếm",
      "category": "baovat",
      "categoryLabel": "Pháp bảo / Bảo vật",
      "status": "known",
      "blurb": "Dung 35 phi kiếm với kiếm linh cũ (hắc kiếm từng uống máu Đằng Lệ) → phi kiếm thuấn di, sắc bén ngang/hơn pháp bảo Nguyên Anh (Ch.127).",
      "detail": [
        {
          "label": "Mô tả",
          "text": "Dung 35 phi kiếm với kiếm linh cũ (hắc kiếm từng uống máu Đằng Lệ) → phi kiếm thuấn di, sắc bén ngang/hơn pháp bảo Nguyên Anh (Ch.127)."
        }
      ]
    },
    {
      "name": "Long cân (pháp bảo)",
      "category": "baovat",
      "categoryLabel": "Pháp bảo / Bảo vật",
      "status": "known",
      "blurb": "Chế từ giao cân giao long; dùng chứa ma đầu và trói/kéo xác địch (\"áo choàng xác người\", Ch.127-131).",
      "detail": [
        {
          "label": "Mô tả",
          "text": "Chế từ giao cân giao long; dùng chứa ma đầu và trói/kéo xác địch (\"áo choàng xác người\", Ch.127-131)."
        }
      ]
    },
    {
      "name": "Cuộn tranh phong ấn linh thú",
      "category": "baovat",
      "categoryLabel": "Pháp bảo / Bảo vật",
      "status": "known",
      "blurb": "Họa trục bí ẩn không hạ được thần thức; bên trong **phong ấn một linh thú** (đôi mắt tam giác tà dị, tiếng rít như giao long). Vương Lâm chưa mở (Ch.134) — hạt giống.",
      "detail": [
        {
          "label": "Mô tả",
          "text": "Họa trục bí ẩn không hạ được thần thức; bên trong **phong ấn một linh thú** (đôi mắt tam giác tà dị, tiếng rít như giao long). Vương Lâm chưa mở (Ch.134) — hạt giống."
        }
      ]
    },
    {
      "name": "Vỏ kiếm cổ (cấp Hóa Thần) — manh mối",
      "category": "baovat",
      "categoryLabel": "Pháp bảo / Bảo vật",
      "status": "unknown",
      "blurb": "vỏ kiếm cổ mà Đằng Hóa Nguyên từng bóp túi nhưng không phá được vẫn còn ở đâu đó (Ch.134). Hạt giống lớn.",
      "detail": [
        {
          "label": "túi trữ vật bị bóp nát thì đồ bên trong vẫn còn",
          "text": "vỏ kiếm cổ mà Đằng Hóa Nguyên từng bóp túi nhưng không phá được vẫn còn ở đâu đó (Ch.134). Hạt giống lớn."
        }
      ]
    },
    {
      "name": "Hơn 100 Kim Đan (chờ tế luyện)",
      "category": "baovat",
      "categoryLabel": "Pháp bảo / Bảo vật",
      "status": "known",
      "blurb": "Chiến lợi phẩm từ Đấu Tà phái; không nuốt sống (gây loạn ngũ hành) mà cất chờ phương pháp tế luyện theo ngũ hành (Ch.134).",
      "detail": [
        {
          "label": "Mô tả",
          "text": "Chiến lợi phẩm từ Đấu Tà phái; không nuốt sống (gây loạn ngũ hành) mà cất chờ phương pháp tế luyện theo ngũ hành (Ch.134)."
        }
      ]
    },
    {
      "name": "Thổ Hành Chu",
      "category": "baovat",
      "categoryLabel": "Pháp bảo / Bảo vật",
      "status": "known",
      "blurb": "Pháp bảo di chuyển trong lòng đất của Bát Cực Ma Quân (mượn), dùng truy đuổi Vương Lâm dưới đất (Ch.136, 139).",
      "detail": [
        {
          "label": "Mô tả",
          "text": "Pháp bảo di chuyển trong lòng đất của Bát Cực Ma Quân (mượn), dùng truy đuổi Vương Lâm dưới đất (Ch.136, 139)."
        }
      ]
    },
    {
      "name": "Ngọc phù cấp Nguyên Anh (Dương Sâm tặng) — đã dùng",
      "category": "baovat",
      "categoryLabel": "Pháp bảo / Bảo vật",
      "status": "known",
      "blurb": "Chứa một kích uy lực Nguyên Anh; **Vương Lâm dùng đỡ một kích của Bát Cực Ma Quân (Ch.139)** — hạt giống Ch.120 đã giải.",
      "detail": [
        {
          "label": "Mô tả",
          "text": "Chứa một kích uy lực Nguyên Anh; **Vương Lâm dùng đỡ một kích của Bát Cực Ma Quân (Ch.139)** — hạt giống Ch.120 đã giải."
        }
      ]
    },
    {
      "name": "Thần Đạo thuật",
      "category": "tienthuat",
      "categoryLabel": "Tiên thuật",
      "status": "known",
      "blurb": "Thuật của Chiến Thần Điện (Hoắc Hồng Phi tinh thông). **Bản nguyên thủy tăng tỷ lệ Kết Anh, chỉ có ở tứ cấp tu chân quốc**; bản Mã Lương biết là bản nhái. Mục tiêu Vương Lâm cuối đợt: mượn xem bản gốc qua **Thủy Kính môn** (Ch.138, 140).",
      "detail": [
        {
          "label": "Mô tả",
          "text": "Thuật của Chiến Thần Điện (Hoắc Hồng Phi tinh thông). **Bản nguyên thủy tăng tỷ lệ Kết Anh, chỉ có ở tứ cấp tu chân quốc**; bản Mã Lương biết là bản nhái. Mục tiêu Vương Lâm cuối đợt: mượn xem bản gốc qua **Thủy Kính môn** (Ch.138, 140)."
        }
      ]
    },
    {
      "name": "Phích Lịch đạn",
      "category": "vatpham",
      "categoryLabel": "Vật phẩm",
      "status": "known",
      "blurb": "Đạn/hỏa khí cổ quái do **Lý Sơn** (đệ tử Huyền Đạo) chế và rao bán. Khi ném vỡ thì nổ bung **bụi bẩn + mùi hôi thối cực nồng bám dai không tẩy được**, kèm chấn động — vũ khí làm nhục đối thủ hơn là sát thương. Bản Lý Sơn bán bị **gài sẵn thần thức** để hắn điều khiển thời điểm nổ mà bày trò. **Vương",
      "detail": [
        {
          "label": "Mô tả",
          "text": "Đạn/hỏa khí cổ quái do **Lý Sơn** (đệ tử Huyền Đạo) chế và rao bán. Khi ném vỡ thì nổ bung **bụi bẩn + mùi hôi thối cực nồng bám dai không tẩy được**, kèm chấn động — vũ khí làm nhục đối thủ hơn là sát thương. Bản Lý Sơn bán bị **gài sẵn thần thức** để hắn điều khiển thời điểm nổ mà bày trò. **Vương Lâm mua 3 viên (Ch.44-45), âm thầm phát hiện và xóa thần thức của Lý Sơn**, rồi dùng chính nó kết hợp Dẫn Lực thuật **hạ nhục Chu Bằng 3 lần liên tiếp** trong tỷ thí (Ch.47-48). Mở màn cho sở thích dùng vật của địch trị địch."
        }
      ]
    },
    {
      "name": "Linh Tuyền thủy",
      "category": "vatpham",
      "categoryLabel": "Vật phẩm",
      "status": "known",
      "blurb": "Nước suối linh ở quê Vương Lâm (mạch Linh Tuyền bí mật), có công hiệu **trú nhan / dưỡng nhan** rõ rệt nên cực được nữ tu sĩ ưa chuộng — vật trao đổi giá trị. Vương Lâm mang ra đổi ở hội giao dịch; **Trương Cuồng** lấy được rồi nhận ra \"người đổi\" chính là Vương Lâm (Ch.47-48). Hoàng Long chân nhân ",
      "detail": [
        {
          "label": "Mô tả",
          "text": "Nước suối linh ở quê Vương Lâm (mạch Linh Tuyền bí mật), có công hiệu **trú nhan / dưỡng nhan** rõ rệt nên cực được nữ tu sĩ ưa chuộng — vật trao đổi giá trị. Vương Lâm mang ra đổi ở hội giao dịch; **Trương Cuồng** lấy được rồi nhận ra \"người đổi\" chính là Vương Lâm (Ch.47-48). Hoàng Long chân nhân sau thu **hai bình Linh Tuyền thủy** khi chất vấn hắn (Ch.50). Là sợi dây nhân quả khiến bí mật Vương Lâm lộ cho Huyền Đạo và dẫn tới việc Chu Bằng về quê hắn (Ch.58). Nguồn nước này gắn với quê nhà — Trương Cuồng bị giết một phần vì định khai thác nó (Ch.59)."
        }
      ]
    },
    {
      "name": "Tạo hóa đan",
      "category": "dandung",
      "categoryLabel": "Đan dược",
      "status": "known",
      "blurb": "Đan dược Vương Hạo lén lấy của tam sư huynh **Lữ Vân Kiệt** để đổi/biếu, dẫn tới việc bị Lữ Vân Kiệt nắm thóp và ép tu tà công (Ch.43). Chi tiết công hiệu không nêu kỹ; vai trò là cái cớ đẩy Vương Hạo vào tay Lữ Vân Kiệt.",
      "detail": [
        {
          "label": "Mô tả",
          "text": "Đan dược Vương Hạo lén lấy của tam sư huynh **Lữ Vân Kiệt** để đổi/biếu, dẫn tới việc bị Lữ Vân Kiệt nắm thóp và ép tu tà công (Ch.43). Chi tiết công hiệu không nêu kỹ; vai trò là cái cớ đẩy Vương Hạo vào tay Lữ Vân Kiệt."
        }
      ]
    },
    {
      "name": "Nhân thọ đan",
      "category": "dandung",
      "categoryLabel": "Đan dược",
      "status": "known",
      "blurb": "Đan kéo dài thọ nguyên mà **Lữ Vân Kiệt** muốn luyện. Để luyện nó, hắn dùng **Lô Hỏa Khai Đỉnh đại pháp** biến người sống (Vương Hạo) thành \"dược lô\" — đốt sinh cơ người làm dược dẫn (Ch.43, 50). Minh chứng cho sự tàn độc của tu chân giới với phàm nhân.",
      "detail": [
        {
          "label": "Mô tả",
          "text": "Đan kéo dài thọ nguyên mà **Lữ Vân Kiệt** muốn luyện. Để luyện nó, hắn dùng **Lô Hỏa Khai Đỉnh đại pháp** biến người sống (Vương Hạo) thành \"dược lô\" — đốt sinh cơ người làm dược dẫn (Ch.43, 50). Minh chứng cho sự tàn độc của tu chân giới với phàm nhân."
        }
      ]
    },
    {
      "name": "Hóa Linh thảo",
      "category": "dandung",
      "categoryLabel": "Đan dược",
      "status": "known",
      "blurb": "Linh thảo **Tôn Đại Trụ** lén cho Vương Lâm ăn nhiều năm để **tán/kìm hãm tu vi**, giữ hắn mãi ở tầng thấp hòng dễ bề khống chế và dò bí mật (khai ra ở Ch.51). Lý do bề ngoài Vương Lâm \"tu mãi không lên tầng\".",
      "detail": [
        {
          "label": "Mô tả",
          "text": "Linh thảo **Tôn Đại Trụ** lén cho Vương Lâm ăn nhiều năm để **tán/kìm hãm tu vi**, giữ hắn mãi ở tầng thấp hòng dễ bề khống chế và dò bí mật (khai ra ở Ch.51). Lý do bề ngoài Vương Lâm \"tu mãi không lên tầng\"."
        }
      ]
    },
    {
      "name": "Tam Thi Tuyến Trùng thảo",
      "category": "dandung",
      "categoryLabel": "Đan dược",
      "status": "known",
      "blurb": "ai uống phải sẽ bị thao túng. **Tôn Đại Trụ** tẩm nó vào \"dược trà\" mời Vương Lâm để biến hắn thành con rối, lấy bí mật (Ch.51). Vương Lâm vạch trò, **ép chính Tôn Đại Trụ uống chén trà đó** rồi tra hỏi và giết — báo hiệu mô-típ \"gậy ông đập lưng ông\" lặp lại.",
      "detail": [
        {
          "label": "luyện khôi lỗi / khống chế người",
          "text": "ai uống phải sẽ bị thao túng. **Tôn Đại Trụ** tẩm nó vào \"dược trà\" mời Vương Lâm để biến hắn thành con rối, lấy bí mật (Ch.51). Vương Lâm vạch trò, **ép chính Tôn Đại Trụ uống chén trà đó** rồi tra hỏi và giết — báo hiệu mô-típ \"gậy ông đập lưng ông\" lặp lại."
        }
      ]
    },
    {
      "name": "Dịch độc Thiên Túc Ngô Công",
      "category": "vatpham",
      "categoryLabel": "Vật phẩm",
      "status": "known",
      "blurb": "Chất dịch độc tê dại tiết ra từ **Thiên Túc Ngô Công** (rết linh thú nghìn chân của Huyền Đạo). Vương Lâm dùng Dẫn Lực thuật **cưỡng đoạt một phần dịch độc** giữa hội giao lưu, đổi lấy việc nhường bình Linh Tuyền thủy — khiến Âu Dương nổi giận (Ch.48-49). Hé lộ cách Vương Lâm tận dụng tài nguyên từ ",
      "detail": [
        {
          "label": "Mô tả",
          "text": "Chất dịch độc tê dại tiết ra từ **Thiên Túc Ngô Công** (rết linh thú nghìn chân của Huyền Đạo). Vương Lâm dùng Dẫn Lực thuật **cưỡng đoạt một phần dịch độc** giữa hội giao lưu, đổi lấy việc nhường bình Linh Tuyền thủy — khiến Âu Dương nổi giận (Ch.48-49). Hé lộ cách Vương Lâm tận dụng tài nguyên từ linh thú đối phương."
        }
      ]
    },
    {
      "name": "Tử Nhạc Tiên Kiếm",
      "category": "baovat",
      "categoryLabel": "Pháp bảo / Bảo vật",
      "status": "known",
      "blurb": "**Trấn phái chi bảo của Hằng Nhạc phái**, bên trong có **long hồn**; do tổ sư Kết Đan Lưu Văn Cử giao chưởng môn **Hoàng Long** giữ. Khi **Phác Nam Tử** (Nguyên Anh, thủy tổ Huyền Đạo) phá sơn môn, kiếm bị **cưỡng đoạt giao cho Âu Dương** (Ch.54). Mất bảo vật trấn phái là dấu mốc Hằng Nhạc suy vong.",
      "detail": [
        {
          "label": "Mô tả",
          "text": "**Trấn phái chi bảo của Hằng Nhạc phái**, bên trong có **long hồn**; do tổ sư Kết Đan Lưu Văn Cử giao chưởng môn **Hoàng Long** giữ. Khi **Phác Nam Tử** (Nguyên Anh, thủy tổ Huyền Đạo) phá sơn môn, kiếm bị **cưỡng đoạt giao cho Âu Dương** (Ch.54). Mất bảo vật trấn phái là dấu mốc Hằng Nhạc suy vong."
        }
      ]
    },
    {
      "name": "Ngọc phù bảo mệnh (một kích Kết Đan)",
      "category": "baovat",
      "categoryLabel": "Pháp bảo / Bảo vật",
      "status": "known",
      "blurb": "Ngọc phù **Lưu Văn Cử** trao Vương Lâm khi cho hắn rời phái về thăm cha mẹ: kích hoạt được **một đòn uy lực cấp Kết Đan** để phòng thân, kèm pháp quyết mở cửa động phủ Tượng Xà sơn (Ch.57-58). Bảo bối hộ mệnh quan trọng của hắn giai đoạn lưu lạc đầu.",
      "detail": [
        {
          "label": "Mô tả",
          "text": "Ngọc phù **Lưu Văn Cử** trao Vương Lâm khi cho hắn rời phái về thăm cha mẹ: kích hoạt được **một đòn uy lực cấp Kết Đan** để phòng thân, kèm pháp quyết mở cửa động phủ Tượng Xà sơn (Ch.57-58). Bảo bối hộ mệnh quan trọng của hắn giai đoạn lưu lạc đầu."
        }
      ]
    },
    {
      "name": "Tử Ngọ Kim Tiễn (phi kiếm giả)",
      "category": "vatpham",
      "categoryLabel": "Vật phẩm",
      "status": "known",
      "blurb": "Phi kiếm **Lý Sơn rao bán dưới danh nghĩa pháp bảo** ở hội giao dịch nhưng thực chất là **hàng giả/kém chất** — một phần trò lừa của Lý Sơn (Ch.44-45). Bối cảnh cho thấy chợ tu chân đầy gian thương.",
      "detail": [
        {
          "label": "Mô tả",
          "text": "Phi kiếm **Lý Sơn rao bán dưới danh nghĩa pháp bảo** ở hội giao dịch nhưng thực chất là **hàng giả/kém chất** — một phần trò lừa của Lý Sơn (Ch.44-45). Bối cảnh cho thấy chợ tu chân đầy gian thương."
        }
      ]
    },
    {
      "name": "Dẫn Lực thuật (đổi tên \"Cầm Long thủ\")",
      "category": "tienthuat",
      "categoryLabel": "Tiên thuật",
      "status": "known",
      "blurb": "**Tiên thuật chủ lực của Vương Lâm suốt Quyển 1**, học từ tàn quyển/khẩu quyết hắn lĩnh hội: vận thần thức tạo **lực hút – kéo – giật** vô hình, đoạt vật trong tay người, kéo địch mất thăng bằng, cướp pháp bảo/đan dược. Là trụ cột tiên pháp (luyện càng lâu càng sinh diệu dụng — Thượng Quan trưởng lã",
      "detail": [
        {
          "label": "Mô tả",
          "text": "**Tiên thuật chủ lực của Vương Lâm suốt Quyển 1**, học từ tàn quyển/khẩu quyết hắn lĩnh hội: vận thần thức tạo **lực hút – kéo – giật** vô hình, đoạt vật trong tay người, kéo địch mất thăng bằng, cướp pháp bảo/đan dược. Là trụ cột tiên pháp (luyện càng lâu càng sinh diệu dụng — Thượng Quan trưởng lão xác nhận, Ch.51). Trong tỷ thí, hắn dùng nó **đoạt binh khí + giật ngã Chu Bằng**, cướp dịch độc Ngô Công (Ch.48). Âu Dương vì sĩ diện bịa rằng đó là \"**Cầm Long thủ thượng cổ**\"; Hoàng Long thuận đà lấy luôn tên này che giấu lai lịch thật cho Vương Lâm (Ch.49). Đây là dạng sơ khai của tuyến năng lực thao túng lực/thần thức về sau."
        }
      ]
    },
    {
      "name": "Lô Hỏa Khai Đỉnh đại pháp",
      "category": "congphap",
      "categoryLabel": "Công pháp",
      "status": "known",
      "blurb": "**Tà công luyện đan** của Lữ Vân Kiệt: biến **người sống thành dược lô**, đốt sinh mệnh lực để luyện đan (nạn nhân là Vương Hạo). Người trúng pháp linh khí lưu chuyển quỷ dị, thọ nguyên cạn nhanh (~1 năm thì chết). Bị sư thúc Hồng Kiểm (họ Mã) nhận ra (Ch.50). Đại diện cho nhánh tà đạo hại người tro",
      "detail": [
        {
          "label": "Mô tả",
          "text": "**Tà công luyện đan** của Lữ Vân Kiệt: biến **người sống thành dược lô**, đốt sinh mệnh lực để luyện đan (nạn nhân là Vương Hạo). Người trúng pháp linh khí lưu chuyển quỷ dị, thọ nguyên cạn nhanh (~1 năm thì chết). Bị sư thúc Hồng Kiểm (họ Mã) nhận ra (Ch.50). Đại diện cho nhánh tà đạo hại người trong môn phái."
        }
      ]
    },
    {
      "name": "Sưu Hồn thuật",
      "category": "tienthuat",
      "categoryLabel": "Tiên thuật",
      "status": "known",
      "blurb": "Thuật **lục soát linh hồn/ký ức** mà **Tôn Đại Trụ** định dùng lên Vương Lâm để moi bí mật (khai ở Ch.51). Chưa kịp thi triển thì bị Vương Lâm giết. Cho thấy bí mật (Nghịch Thiên châu) của Vương Lâm luôn bị nhòm ngó.",
      "detail": [
        {
          "label": "Mô tả",
          "text": "Thuật **lục soát linh hồn/ký ức** mà **Tôn Đại Trụ** định dùng lên Vương Lâm để moi bí mật (khai ở Ch.51). Chưa kịp thi triển thì bị Vương Lâm giết. Cho thấy bí mật (Nghịch Thiên châu) của Vương Lâm luôn bị nhòm ngó."
        }
      ]
    },
    {
      "name": "Khôi Lỗi thuật (sơ truyền Ch.60)",
      "category": "tienthuat",
      "categoryLabel": "Tiên thuật",
      "status": "known",
      "blurb": "Tư Đồ Nam cố ý bịa thêm bước \"mổ bụng moi ngũ tạng\" nhằm từng bước tiêm nhiễm tâm tính tàn nhẫn — tức bản Vương Lâm học lúc đầu KHÔNG phải bản chuẩn (mưu đồ dắt hắn vào ma đạo). Khôi Lỗi thuật về sau (Ch.121-140) đã thành kỹ năng quen thuộc của hắn.",
      "detail": [
        {
          "label": "luyện người/xác thành con rối (khôi lỗi) phục tùng tuyệt đối**, do **Tư Đồ Nam truyền cho Vương Lâm ở Ch.60**. Vương Lâm dùng ngay lên **Chu Bằng** (sau khi Tư Đồ Nam đóng băng trọng thương hắn): biến Chu Bằng thành khôi lỗi, sai quay về Huyền Đạo ngầm bảo vệ cha mẹ Vương Lâm và giết kẻ bất lợi. **Lưu ý lịch đại",
          "text": "Tư Đồ Nam cố ý bịa thêm bước \"mổ bụng moi ngũ tạng\" nhằm từng bước tiêm nhiễm tâm tính tàn nhẫn — tức bản Vương Lâm học lúc đầu KHÔNG phải bản chuẩn (mưu đồ dắt hắn vào ma đạo). Khôi Lỗi thuật về sau (Ch.121-140) đã thành kỹ năng quen thuộc của hắn."
        }
      ]
    },
    {
      "name": "Hoàng Tuyền Thăng Khiếu Quyết (lời hứa Ch.52)",
      "category": "congphap",
      "categoryLabel": "Công pháp",
      "status": "known",
      "blurb": "đây chính là tiền đề của **Hoàng Tuyền Đạo / Hoàng Tuyền Thăng Khiếu Quyết** (9 tầng, 3 hàn đan) mà tới Ch.127 Vương Lâm đã tu tới đại thành — hạt giống gieo từ Quyển 1 nay đã nảy.",
      "detail": [
        {
          "label": "Tư Đồ Nam hứa truyền cho Vương Lâm khi hắn vào Trúc Cơ** (Ch.52). Lão chê toàn bộ công pháp trong Tàng Kinh Các Hằng Nhạc là \"đồ bỏ\", chỉ công pháp của lão mới xứng. **Đối chiếu lịch đại",
          "text": "đây chính là tiền đề của **Hoàng Tuyền Đạo / Hoàng Tuyền Thăng Khiếu Quyết** (9 tầng, 3 hàn đan) mà tới Ch.127 Vương Lâm đã tu tới đại thành — hạt giống gieo từ Quyển 1 nay đã nảy."
        }
      ]
    },
    {
      "name": "Thủy Mạc chiết xạ",
      "category": "tienthuat",
      "categoryLabel": "Tiên thuật",
      "status": "known",
      "blurb": "Tuyệt kỹ thủy hệ của **Liễu Phong** (đơn thủy linh căn, Huyền Đạo): dựng **màn nước phản xạ/bẻ cong** đòn tấn công ngược lại đối thủ; cần tu vi ~tầng 8 mới phá nổi. Dùng đánh bại Triệu Long ở trận 1 tỷ thí (Ch.47).",
      "detail": [
        {
          "label": "Mô tả",
          "text": "Tuyệt kỹ thủy hệ của **Liễu Phong** (đơn thủy linh căn, Huyền Đạo): dựng **màn nước phản xạ/bẻ cong** đòn tấn công ngược lại đối thủ; cần tu vi ~tầng 8 mới phá nổi. Dùng đánh bại Triệu Long ở trận 1 tỷ thí (Ch.47)."
        }
      ]
    },
    {
      "name": "Liên Hoa kiếm khí",
      "category": "tienthuat",
      "categoryLabel": "Tiên thuật",
      "status": "known",
      "blurb": "Ch.1-140 (Quyển 2 — arc Tu Ma hải & Kết Đan). Khối 121-140 bổ sung: **Giả Đan cảnh giới**, **Kết Anh** (mục tiêu), **cấp bậc linh thú (dị/linh/hoang/tiên × hạ/trung/thượng) + đối chiếu cảnh giới người**, giao long/long đan/cốt tủy, **Hoàng Tuyền chi cảnh + Hoàng tuyền băng diễm + tam đan hợp nhất**,",
      "detail": [
        {
          "label": "Triệu Long** (đệ tử Hằng Nhạc): kiếm khí tụ hình hoa sen. Bị Thủy Mạc chiết xạ của Liễu Phong khắc chế, thua trận 1 (Ch.47). Mục phụ minh họa tương quan công pháp hai phái.\n---\n\n**Cập nhật",
          "text": "Ch.1-140 (Quyển 2 — arc Tu Ma hải & Kết Đan). Khối 121-140 bổ sung: **Giả Đan cảnh giới**, **Kết Anh** (mục tiêu), **cấp bậc linh thú (dị/linh/hoang/tiên × hạ/trung/thượng) + đối chiếu cảnh giới người**, giao long/long đan/cốt tủy, **Hoàng Tuyền chi cảnh + Hoàng tuyền băng diễm + tam đan hợp nhất**, **thôn phệ Kim Đan (Thông Phệ đại pháp)**, **đan lô phân phẩm (Phiên Ưng lô cửu phẩm, Bách Thú Linh lô ngũ phẩm)**, **Vạn Ma Bách Nhật Tru Sát Lệnh + tu đan**, **Bát Trảo thần thức**, **Tử Chú thuật (lưu ý: Vương Lâm thực ra dùng Cực cảnh, người ngoài hiểu nhầm)**, Thiên Ly/Lập Anh/Anh Biến đan, Thủy tinh phi kiếm, long cân, cuộn tranh phong ấn linh thú, manh mối vỏ kiếm cổ, >100 Kim Đan, Thổ Hành Chu, phẩm chất khí âm hàn (Thiên Địa Huyền Hoàng, thập nhất giai), các trận (Phệ Huyết Thiên Ma, Cửu Ly thi cốt/Giao Long, Đấu Long đại trận), Thần Đạo thuật + Thủy Kính môn, Mộng Cảnh né Tru Sát Lệnh, địa lý Tu Ma hải/Chu Vũ đại lục/Thi Cốc/cốt hải."
        },
        {
          "label": "Lưu ý lịch đại",
          "text": "Cực cảnh thần thức bị hiểu nhầm là Tử Chú thuật xuyên suốt arc — đây là ngòi truyện chứ không phải dữ kiện về năng lực thật của Vương Lâm."
        },
        {
          "label": "Bổ sung 2026-06-04 (rà Quyển 1)",
          "text": "thêm khối ĐAN DƯỢC/PHÁP BẢO/CÔNG PHÁP đợt Ch.41-60 (17 mục) — Phích Lịch đạn, Linh Tuyền thủy, Tạo hóa/Nhân thọ đan, Hóa Linh thảo, Tam Thi Tuyến Trùng thảo, dịch độc Ngô Công, Tử Nhạc Tiên Kiếm, ngọc phù bảo mệnh, Tử Ngọ Kim Tiễn, Dẫn Lực thuật (Cầm Long thủ), Lô Hỏa Khai Đỉnh đại pháp, Sưu Hồn thuật, Khôi Lỗi thuật (sơ truyền), Hoàng Tuyền Thăng Khiếu Quyết (lời hứa), Thủy Mạc chiết xạ, Liên Hoa kiếm khí. Các đợt Quyển 1 khác (Ch.1-40, 61-100) vẫn cần rà bổ sung tương tự khi có văn bản gốc."
        }
      ]
    }
  ]
}